pylanetary/__init__.py
pylanetary/_astropy_init.py
pylanetary/conftest.py
pylanetary/data/README.rst
pylanetary/extern/__init__.py
pylanetary/navigation/__init__.py
pylanetary/navigation/core.py
pylanetary/navigation/tests/__init__.py
pylanetary/navigation/tests/test_nav.py
pylanetary/navigation/tests/test_nav_remote.py
pylanetary/navigation/tests/data/__init__.py
pylanetary/navigation/tests/data/hlsp_wfcj_hst_wfc3-uvis_jupiter-2017-pj07_f631n_v2_0711ut0947-nav.fits
pylanetary/navigation/tests/data/keck_uranus.npy
pylanetary/navigation/tests/data/lat_g.npy
pylanetary/navigation/tests/data/lat_g_keck.npy
pylanetary/navigation/tests/data/ldmodel.npy
pylanetary/navigation/tests/data/ldmodel_jupiter_minnaert.npy
pylanetary/navigation/tests/data/lon_w.npy
pylanetary/navigation/tests/data/mu.npy
pylanetary/navigation/tests/data/mu0_projected.npy
pylanetary/navigation/tests/data/mu_projected.npy
pylanetary/navigation/tests/data/nepk99_IF.fits
pylanetary/navigation/tests/data/projected.npy
pylanetary/navigation/tests/data/projected_custom.npy
pylanetary/navigation/tests/data/projected_polar.npy
pylanetary/navigation/tests/data/surf_n.npy
pylanetary/rings/__init__.py
pylanetary/rings/core.py
pylanetary/rings/data/Jupiter_refs.txt
pylanetary/rings/data/Jupiter_ring_data.hdf5
pylanetary/rings/data/Neptune_refs.txt
pylanetary/rings/data/Neptune_ring_data.hdf5
pylanetary/rings/data/Saturn_refs.txt
pylanetary/rings/data/Saturn_ring_data.hdf5
pylanetary/rings/data/Uranus_refs.txt
pylanetary/rings/data/Uranus_ring_data.hdf5
pylanetary/rings/data/__init__.py
pylanetary/rings/data/build_ring_tables.py
pylanetary/rings/tests/__init__.py
pylanetary/rings/tests/test_ellipse_math.py
pylanetary/rings/tests/test_ringmodel.py
pylanetary/rings/tests/test_ringmodel_remote.py
pylanetary/rings/tests/test_vector_math.py
pylanetary/rings/tests/data/as_2d_array_testarr.npy
pylanetary/rings/tests/data/ura_system_testarr.npy
pylanetary/rings/tests/data/wedges_testarr.npy
pylanetary-0.1.0.dist-info/METADATA
pylanetary-0.1.0.dist-info/WHEEL
pylanetary-0.1.0.dist-info/top_level.txt
pylanetary-0.1.0.dist-info/RECORD
