Metadata-Version: 2.1
Name: pylanetary
Version: 0.1.0
Summary: data processing and modeling tools for ring, moon, and planet observations
Author-email: Ned Molter <ned.molter@gmail.com>
Maintainer-email: Ned Molter <ned.molter@gmail.com>
License: GNU GENERAL PUBLIC LICENSE
Project-URL: Source, https://github.com/emolter/pylanetary
Project-URL: Docs, https://pylanetary.readthedocs.io/en/latest/
Project-URL: Bug Reports, https://github.com/emolter/pylanetary/issues
Keywords: astronomy,astrophysics,astropy,solar system,planetary,planet
Classifier: Development Status :: 3 - Alpha
Classifier: Intended Audience :: Science/Research
Classifier: Topic :: Scientific/Engineering :: Astronomy
Classifier: License :: OSI Approved :: GNU General Public License (GPL)
Classifier: Programming Language :: Python :: 3
Classifier: Programming Language :: Python :: 3.9
Classifier: Programming Language :: Python :: 3.10
Classifier: Programming Language :: Python :: 3.11
Classifier: Programming Language :: Python :: 3.12
Classifier: Programming Language :: Python :: 3 :: Only
Requires-Python: >=3.9
Requires-Dist: astropy >=4.3.0
Requires-Dist: astroquery >=0.4.7.dev8893
Requires-Dist: beautifulsoup4 >=4.11.1
Requires-Dist: cartopy
Requires-Dist: extension-helpers >=1.0.0
Requires-Dist: h5py >=3.0.0
Requires-Dist: image-registration >=0.2.8
Requires-Dist: matplotlib >=3.5.1
Requires-Dist: numpy >=1.21.6
Requires-Dist: photutils >=1.3.0
Requires-Dist: pytest >=6.2.4
Requires-Dist: pytest-astropy-header >=0.2.2
Requires-Dist: pyyaml
Requires-Dist: scikit-image >=0.18.3
Requires-Dist: scipy >=1.7.0
Requires-Dist: setuptools >=68.0.0
Requires-Dist: setuptools-scm >=7.0.5
Requires-Dist: sphinx-astropy >=1.7.0
Requires-Dist: sphinx-pyproject
Requires-Dist: nbsphinx
Provides-Extra: docs
Requires-Dist: sphinx-astropy ; extra == 'docs'
Requires-Dist: sphinx-pyproject ; extra == 'docs'
Provides-Extra: test
Requires-Dist: pytest-astropy ; extra == 'test'
